LWWElementGraph/LWWElementGraph.py
LWWElementGraph/LWWElementSet.py
LWWElementGraph/__init__.py
LWWElementGraph-1.0.5.dist-info/LICENSE
LWWElementGraph-1.0.5.dist-info/METADATA
LWWElementGraph-1.0.5.dist-info/WHEEL
LWWElementGraph-1.0.5.dist-info/top_level.txt
LWWElementGraph-1.0.5.dist-info/RECORD
