Metadata-Version: 2.1
Name: LWWElementGraph
Version: 1.0.5
Summary: Module for a lightweight LWWElementGraph
Home-page: https://github.com/krohak/CDRT
Author: krohak
Author-email: rohaksinghal14@gmail.com
License: MIT
Platform: UNKNOWN
Classifier: License :: OSI Approved :: MIT License
Classifier: Programming Language :: Python :: 3
Classifier: Programming Language :: Python :: 3.7
License-File: LICENSE
